Workbook

Sheet Summary
A1: Lumi PCB v1: budget
A2: Prices checked 2026-10-30. Change inputs on the Inputs and Parts tabs; everything here updates.
B4: USD | C4: CAD
A5: Prototype run A, all in | B5: =Prototypes!B17 -> 188.6395 | C5: =Prototypes!C17 -> 264.0953
A6: ... per prototype | B6: =Prototypes!B18 -> 37.727899 | C6: =Prototypes!C18 -> 52.819059
A7: Prototype run B, all in | B7: =Prototypes!D17 -> 268.70042 | C7: =Prototypes!E17 -> 376.18059
A8: ... per prototype | B8: =Prototypes!D18 -> 26.870042 | C8: =Prototypes!E18 -> 37.618059
A9: One Lumi in a 100 run | B9: ='Per unit'!B14 -> 11.717685 | C9: ='Per unit'!C14 -> 16.404759
A10: One Lumi in a 1,000 run | B10: ='Per unit'!D14 -> 8.025885 | C10: ='Per unit'!E14 -> 11.236239
A12: Run A boards | B12: =Prototypes!B4 -> 5
A13: Run B boards | B13: =Prototypes!D4 -> 10
A14: Exchange rate (CAD per USD) | B14: =Inputs!$B$5 -> 1.4
A15: GST on imports | B15: =Inputs!$B$6 -> 0.05
A17: Colour key
A18: Blue text: an input you can change
A19: Black text: a formula
A20: Green text: a value pulled from another tab
A21: Yellow fill: key assumption
A23: Includes: board built by JLCPCB, screen, battery, printed case,
A24: shipping to Canada, GST and courier brokerage.
A25: Excludes: tools, certification, packaging and your time.

Sheet Inputs
A1: Inputs: edit the blue cells
A2: Prices in USD, checked 2026-10-30. Yellow = key assumptions.
A4: Assumption | B4: Value | C4: Note
A5: Exchange rate (CAD per 1 USD) | B5: 1.4 | C5: About 1.40-1.43 through October 2026 (moneyexchangerate.org).
A6: GST on imports | B6: 0.05 | C6: Federal GST. HST provinces pay 13-15% instead: change this.
A7: Courier brokerage per parcel (CAD) | B7: 15 | C7: Forum reports of DHL/UPS clearance fees for Canada.
A8: Courier parcels per prototype run | B8: 2 | C8: JLCPCB boards + screens; batteries come by ground post.
A10: JLCPCB assembly
A11: Economic assembly setup (per order) | B11: 8 | C11: JLCPCB help: PCB assembly price.
A12: Stencil (per order) | B12: 1.5 | C12: JLCPCB help: PCB assembly price.
A13: Extended part types on the board | B13: 8 | C13: U1-U4, D1, J1, J2, SW1.
A14: Fee per Extended part type | B14: 3 | C14: Official FAQ says $3; one source says $1.50 since Dec 2025.
A15: Hand-soldering setup (USB-C shell legs) | B15: 3.5 | C15: JLCPCB help.
A16: Standard assembly setup (100+ runs) | B16: 25 | C16: JLCPCB help (older price page).
A17: SMT solder joints per board | B17: 165 | C17: Counted from the board's pads (approx.).
A18: Cost per SMT joint | B18: 0.0017 | C18: JLCPCB Economic assembly.
A19: Hand-soldered joints per board | B19: 4 | C19: USB-C shell legs.
A20: Cost per hand-soldered joint | B20: 0.0173 | C20: JLCPCB help.
A22: Bare boards (31 x 33 mm, 2 layers, 1.0 mm)
A23: Order of 5 boards | B23: 4 | C23: Estimate; $2 offer is for 1.6 mm boards.
A24: Order of 10 boards | B24: 6 | C24: Estimate.
A25: Per board at 100 | B25: 0.25 | C25: Estimate.
A26: Per board at 1,000 | B26: 0.08 | C26: Estimate.
A28: Shipping
A29: JLCPCB boards to Canada (DHL) | B29: 25 | C29: Forum reports: ~$17-25 for small orders.
A30: Screens from BuyDisplay | B30: 15 | C30: Estimate.
A31: Batteries (AliExpress, ground) | B31: 4 | C31: Estimate.
A32: Shipping share per unit at 100 | B32: 0.6 | C32: Estimate (air freight).
A33: Shipping share per unit at 1,000 | B33: 0.2 | C33: Estimate (air freight).

Sheet Parts
A1: Parts: price each (USD) by how many you buy
A2: Blue = edit. Prices from LCSC/JLCPCB listings; 'Yes' in Estimate = no live quote seen.
A4: Ref | B4: Part | C4: LCSC | D4: 5-10 boards | E4: 100 | F4: 1,000 | G4: Estimate? | H4: Note
A5: U1 | B5: ESP32-C3-WROOM-02-N4 module | C5: C2934560 | D5: 3.4 | E5: 2.6 | F5: 2.09 | G5: No
A6: U2 | B6: LIS2DH12TR accelerometer | C6: C110926 | D6: 0.57 | E6: 0.39 | F6: 0.36 | G6: No
A7: J2 | B7: Hirose FH12-30S-0.5SH screen connector | C7: C506793 | D7: 0.72 | E7: 0.62 | F7: 0.5 | G7: Yes
A8: D1 | B8: USBLC6-2SC6 USB ESD | C8: C7519 | D8: 0.2 | E8: 0.15 | F8: 0.11 | G8: Yes
A9: J1 | B9: USB-C receptacle TYPE-C-31-M-12 | C9: C165948 | D9: 0.18 | E9: 0.13 | F9: 0.1 | G9: No
A10: U4 | B10: RT9080-33GJ5 3.3 V regulator | C10: C841192 | D10: 0.12 | E10: 0.09 | F10: 0.07 | G10: Yes
A11: U3 | B11: TP4054 charger | C11: C32574 | D11: 0.06 | E11: 0.05 | F11: 0.04 | G11: Yes
A12: SW1 | B12: MSK12C02 slide switch | C12: C431540 | D12: 0.06 | E12: 0.05 | F12: 0.04 | G12: Yes
A13: R/C | B13: 27 resistors and capacitors (JLCPCB Basic) | C13: various | D13: 0.1 | E13: 0.06 | F13: 0.04 | G13: Yes
B14: Board parts, per board | D14: =SUM(D5:D13) -> 5.41 | E14: =SUM(E5:E13) -> 4.14 | F14: =SUM(F5:F13) -> 3.35
A16: Item | B16: Part | D16: 5-10 units | E16: 100 | F16: 1,000 | H16: Note
A17: Screen | B17: BuyDisplay ER-OLED0.96-1 plug-in OLED | D17: 2.49 | E17: 2.23 | F17: 1.7 | H17: 1,000: est. factory quote
A18: Battery | B18: 503030 LiPo ~500 mAh, protected, UN38.3 | D18: 6 | E18: 2.5 | F18: 1.4 | H18: est.
A19: Case | B19: Mini Lumi PCB case, PLA, ~17 g at $25/kg | D19: 0.45 | E19: 0.45 | F19: 0.45 | H19: your printer; ~2.5 h
A20: Sundries | B20: foam tape, Kapton, battery wire | D20: 0.15 | E20: 0.1 | F20: 0.06 | H20: est.

Sheet Prototypes
A1: Prototype runs, all in
A2: Edit the quantities in row 4 (blue). Bare-board order prices are on Inputs.
B3: Run A (USD) | C3: Run A (CAD) | D3: Run B (USD) | E3: Run B (CAD)
A4: Boards in the run | B4: 5 | D4: 10
A5: Board parts | B5: =$B$4*Parts!$D$14 -> 27.05 | C5: =B5*Inputs!$B$5 -> 37.87 | D5: =$D$4*Parts!$D$14 -> 54.1 | E5: =D5*Inputs!$B$5 -> 75.74
A6: Assembly (solder joints) | B6: =$B$4*(Inputs!$B$17*Inputs!$B$18+Inputs!$B$19*Inputs!$B$20) -> 1.7485 | C6: =B6*Inputs!$B$5 -> 2.4479 | D6: =$D$4*(Inputs!$B$17*Inputs!$B$18+Inputs!$B$19*Inputs!$B$20) -> 3.497 | E6: =D6*Inputs!$B$5 -> 4.8958
A7: Bare boards (one order) | B7: =Inputs!$B$23 -> 4 | C7: =B7*Inputs!$B$5 -> 5.6 | D7: =Inputs!$B$24 -> 6 | E7: =D7*Inputs!$B$5 -> 8.4
A8: Assembly setup, stencil, Extended-part fees | B8: =Inputs!$B$11+Inputs!$B$12+Inputs!$B$13*Inputs!$B$14+Inputs!$B$15 -> 37 | C8: =B8*Inputs!$B$5 -> 51.8 | D8: =Inputs!$B$11+Inputs!$B$12+Inputs!$B$13*Inputs!$B$14+Inputs!$B$15 -> 37 | E8: =D8*Inputs!$B$5 -> 51.8
A9: Screens | B9: =$B$4*Parts!$D$17 -> 12.45 | C9: =B9*Inputs!$B$5 -> 17.43 | D9: =$D$4*Parts!$D$17 -> 24.9 | E9: =D9*Inputs!$B$5 -> 34.86
A10: Batteries | B10: =$B$4*Parts!$D$18 -> 30 | C10: =B10*Inputs!$B$5 -> 42 | D10: =$D$4*Parts!$D$18 -> 60 | E10: =D10*Inputs!$B$5 -> 84
A11: Cases (printed) and sundries | B11: =$B$4*(Parts!$D$19+Parts!$D$20) -> 3 | C11: =B11*Inputs!$B$5 -> 4.2 | D11: =$D$4*(Parts!$D$19+Parts!$D$20) -> 6 | E11: =D11*Inputs!$B$5 -> 8.4
A12: Shipping: JLCPCB boards (DHL) | B12: =Inputs!$B$29 -> 25 | C12: =B12*Inputs!$B$5 -> 35 | D12: =Inputs!$B$29 -> 25 | E12: =D12*Inputs!$B$5 -> 35
A13: Shipping: screens | B13: =Inputs!$B$30 -> 15 | C13: =B13*Inputs!$B$5 -> 21 | D13: =Inputs!$B$30 -> 15 | E13: =D13*Inputs!$B$5 -> 21
A14: Shipping: batteries | B14: =Inputs!$B$31 -> 4 | C14: =B14*Inputs!$B$5 -> 5.6 | D14: =Inputs!$B$31 -> 4 | E14: =D14*Inputs!$B$5 -> 5.6
A15: GST on imports | B15: =Inputs!$B$6*SUM(B5:B14) -> 7.962425 | C15: =B15*Inputs!$B$5 -> 11.147395 | D15: =Inputs!$B$6*SUM(D5:D14) -> 11.77485 | E15: =D15*Inputs!$B$5 -> 16.48479
A16: Courier brokerage | B16: =Inputs!$B$8*Inputs!$B$7/Inputs!$B$5 -> 21.428571 | C16: =B16*Inputs!$B$5 -> 30 | D16: =Inputs!$B$8*Inputs!$B$7/Inputs!$B$5 -> 21.428571 | E16: =D16*Inputs!$B$5 -> 30
A17: Total | B17: =SUM(B5:B16) -> 188.6395 | C17: =SUM(C5:C16) -> 264.0953 | D17: =SUM(D5:D16) -> 268.70042 | E17: =SUM(E5:E16) -> 376.18059
A18: Per prototype | B18: =IFERROR(B17/$B$4,0) -> 37.727899 | C18: =IFERROR(C17/$B$4,0) -> 52.819059 | D18: =IFERROR(D17/$D$4,0) -> 26.870042 | E18: =IFERROR(E17/$D$4,0) -> 37.618059
A20: Fixed costs (setup, stencil, Extended-part fees, shipping) are the same for any run size, which is why 10 boards cost far less than twice 5.

Sheet Per unit
A1: Cost of one Lumi at volume
A2: Uses the 100 and 1,000 price columns on Parts. Edit run sizes in row 4.
B3: 100 run (USD) | C3: 100 run (CAD) | D3: 1,000 run (USD) | E3: 1,000 run (CAD)
A4: Units in the run | B4: 100 | D4: 1000
A5: Board parts | B5: =Parts!$E$14 -> 4.14 | C5: =B5*Inputs!$B$5 -> 5.796 | D5: =Parts!$F$14 -> 3.35 | E5: =D5*Inputs!$B$5 -> 4.69
A6: Bare board | B6: =Inputs!$B$25 -> 0.25 | C6: =B6*Inputs!$B$5 -> 0.35 | D6: =Inputs!$B$26 -> 0.08 | E6: =D6*Inputs!$B$5 -> 0.112
A7: Assembly (solder joints) | B7: =Inputs!$B$17*Inputs!$B$18+Inputs!$B$19*Inputs!$B$20 -> 0.3497 | C7: =B7*Inputs!$B$5 -> 0.48958 | D7: =Inputs!$B$17*Inputs!$B$18+Inputs!$B$19*Inputs!$B$20 -> 0.3497 | E7: =D7*Inputs!$B$5 -> 0.48958
A8: Assembly setup and fees, shared | B8: =IFERROR((Inputs!$B$16+Inputs!$B$12+Inputs!$B$13*Inputs!$B$14+Inputs!$B$15)/$B$4,0) -> 0.54 | C8: =B8*Inputs!$B$5 -> 0.756 | D8: =IFERROR((Inputs!$B$16+Inputs!$B$12+Inputs!$B$13*Inputs!$B$14+Inputs!$B$15)/$D$4,0) -> 0.054 | E8: =D8*Inputs!$B$5 -> 0.0756
A9: Screen | B9: =Parts!$E$17 -> 2.23 | C9: =B9*Inputs!$B$5 -> 3.122 | D9: =Parts!$F$17 -> 1.7 | E9: =D9*Inputs!$B$5 -> 2.38
A10: Battery | B10: =Parts!$E$18 -> 2.5 | C10: =B10*Inputs!$B$5 -> 3.5 | D10: =Parts!$F$18 -> 1.4 | E10: =D10*Inputs!$B$5 -> 1.96
A11: Case and sundries | B11: =Parts!$E$19+Parts!$E$20 -> 0.55 | C11: =B11*Inputs!$B$5 -> 0.77 | D11: =Parts!$F$19+Parts!$F$20 -> 0.51 | E11: =D11*Inputs!$B$5 -> 0.714
A12: Shipping share | B12: =Inputs!$B$32 -> 0.6 | C12: =B12*Inputs!$B$5 -> 0.84 | D12: =Inputs!$B$33 -> 0.2 | E12: =D12*Inputs!$B$5 -> 0.28
A13: GST on imports | B13: =Inputs!$B$6*SUM(B5:B12) -> 0.557985 | C13: =B13*Inputs!$B$5 -> 0.781179 | D13: =Inputs!$B$6*SUM(D5:D12) -> 0.382185 | E13: =D13*Inputs!$B$5 -> 0.535059
A14: Per unit | B14: =SUM(B5:B13) -> 11.717685 | C14: =SUM(C5:C13) -> 16.404759 | D14: =SUM(D5:D13) -> 8.025885 | E14: =SUM(E5:E13) -> 11.236239
A15: Whole run | B15: =B14*$B$4 -> 1171.7685 | C15: =C14*$B$4 -> 1640.4759 | D15: =D14*$D$4 -> 8025.885 | E15: =E14*$D$4 -> 11236.239

Sheet Sources
A1: Sources
A3: What | B3: Link
A4: JLCPCB: what the PCB assembly price includes | B4: https://jlcpcb.com/help/article/pcb-assembly-price
A5: JLCPCB PCBA price overview (feeder fee change) | B5: https://techoverflow.net/2024/04/09/jlcpcb-pcba-assembly-price-overview/
A6: JLCPCB $2 PCB offer | B6: https://jlcpcb.com/blog/free-assembly-for-1-6-layer-pcbs-and-discounts-on-8-20-layer-pcba
A7: ESP32-C3-WROOM-02-N4 on LCSC | B7: https://www.lcsc.com/product-detail/WiFi-Modules_Espressif-Systems-ESP32-C3-WROOM-02-N4_C2934560.html
A8: LIS2DH12TR on LCSC | B8: https://www.lcsc.com/product-image/C110926.html
A9: TYPE-C-31-M-12 on LCSC | B9: https://lcsc.com/product-detail/USB-Connectors_Korean-Hroparts-Elec-TYPE-C-31-M-12_C165948.html
A10: Hirose FH12-30S-0.5SH on LCSC | B10: https://lcsc.com/product-detail/FFC-FPC-Flat-Flexible-Connector-Assemblies_HRS-Hirose-FH12-30S-0-5SH-55_C506793.html
A11: USBLC6-2SC6 on JLCPCB | B11: https://jlcpcb.com/partdetail/C7519
A12: BuyDisplay ER-OLED0.96-1 | B12: https://buydisplay.com/blue-128x64-0-96-inch-oled-display-top-contact-connector-fpc-ssd1306
A13: 503030 500 mAh protected LiPo (retail reference) | B13: https://www.walmart.com/ip/seot/5362991161
A14: Shipping and brokerage to Canada (forum reports) | B14: https://forum.kicad.info/t/alternatives-to-jlcpcb-or-pcbway-for-canadian-hobbyist/61624
... A16: USD/CAD, October 2026 | B16: https://moneyexchangerate.org/currencyexchange/usd/cad
